{"id": "cap-2026-06-24", "title": "Mes captures — 2026-06-24", "type": "personal", "date": "2026-06-24", "cards": [{"id": "cap0624-01", "fr": "J'espère que tu te rétablis vite", "en": "Hope you recover soon", "note": "Rétablis is more commonly used than remettras in this context", "scene": "Mes captures", "isPersonal": true, "audio": "packs/audio/cap0624-01.mp3"}, {"id": "cap0624-02", "fr": "Ne me fais pas porter le chapeau !", "en": "Don't blame me!", "note": "Idiomatic expression meaning to take responsibility for something, often unfairly", "scene": "Mes captures", "isPersonal": true, "audio": "packs/audio/cap0624-02.mp3"}, {"id": "cap0624-03", "fr": "Ne m'en veux pas !", "en": "Don't be mad at me!", "note": "Used to apologize or ask for forgiveness, informal", "scene": "Mes captures", "isPersonal": true, "audio": "packs/audio/cap0624-03.mp3"}, {"id": "cap0624-04", "fr": "D'où tiens-tu cela ?", "en": "Where did you get that from?", "note": "Use 'cela' for a more formal tone, or omit it in informal conversations", "scene": "Mes captures", "isPersonal": true, "audio": "packs/audio/cap0624-04.mp3"}, {"id": "cap0624-05", "fr": "J'espère que tu te rétablis vite", "en": "Hope you recover soon", "note": "Rétablis is more commonly used than remettras in this context", "scene": "Mes captures", "isPersonal": true, "audio": "packs/audio/cap0624-05.mp3"}, {"id": "cap0624-06", "fr": "Ne me fais pas porter le chapeau !", "en": "Don't blame me!", "note": "Expression idiomatique pour refuser d'assumer la responsabilité", "scene": "Mes captures", "isPersonal": true, "audio": "packs/audio/cap0624-06.mp3"}, {"id": "cap0624-07", "fr": "Ne m'en veux pas !", "en": "Don't be mad at me", "note": "Used to apologize or ask for forgiveness, informal", "scene": "Mes captures", "isPersonal": true, "audio": "packs/audio/cap0624-07.mp3"}, {"id": "cap0624-08", "fr": "D'où tiens-tu cela ?", "en": "Where did you get that from?", "note": "Use 'cela' for a more formal tone, or omit it for an informal conversation", "scene": "Mes captures", "isPersonal": true, "audio": "packs/audio/cap0624-08.mp3"}], "owner": "matthew"}